rougail/output_doc/__init__.py
rougail/output_doc/annotator.py
rougail/output_doc/config.py
rougail/output_doc/i18n.py
rougail/output_doc/locale/fr/LC_MESSAGES/rougail_output_doc.mo
rougail/output_doc/output/__init__.py
rougail/output_doc/output/asciidoc.py
rougail/output_doc/output/github.py
rougail_output_doc-0.1.0.dist-info/LICENSE
rougail_output_doc-0.1.0.dist-info/WHEEL
rougail_output_doc-0.1.0.dist-info/METADATA
rougail_output_doc-0.1.0.dist-info/RECORD
